chempropstereo/__init__.py
chempropstereo/_version.py
chempropstereo/tests/__init__.py
chempropstereo/tests/test_chempropstereo.py
chempropstereo-0.0.0.dist-info/LICENSE.md
chempropstereo-0.0.0.dist-info/METADATA
chempropstereo-0.0.0.dist-info/WHEEL
chempropstereo-0.0.0.dist-info/top_level.txt
chempropstereo-0.0.0.dist-info/RECORD
