Metadata-Version: 2.2
Name: chempropstereo
Version: 0.0.0
Summary: Stereochemistry Extention for Chemprop
Author-email: Charlles Abreu <craabreu@gmail.com>
License: MIT
Classifier: License :: OSI Approved :: MIT License
Classifier: Programming Language :: Python :: 3.9
Classifier: Programming Language :: Python :: 3.10
Classifier: Programming Language :: Python :: 3.11
Classifier: Programming Language :: Python :: 3.12
Requires-Python: >=3.9
License-File: LICENSE.md
Requires-Dist: chemprop
Provides-Extra: test
Requires-Dist: pytest>=6.1.2; extra == "test"
Requires-Dist: pytest-runner; extra == "test"
